{
    "categories": [
      { "id": 1, "name": "ഓട്ടോ ഡ്രൈവർ" ,"img":"../../../public/images/auto.png"},
      { "id": 2, "name": "പെയിന്റിംഗ്" ,"img":"../../../public/images/wall painting.webp"},
      { "id": 3, "name": "വയറിങ്","img":"../../../images/electriiotion.jfif" },
      { "id": 4, "name": "ഷോപ്പുകൾ","img":"../../../public/images/Shope.avif"},
      { "id": 9, "name": "സെന്ററിങ്","img":"../../../public/images/Centring.png" },
      { "id": 10, "name": "പടവ്" ,"img":"../../../public/images/Padavu.png"},
      { "id": 11, "name": "തേപ്പ്" ,"img":"../../../public/images/theyppu.png"},
      { "id": 12, "name": "ടൈൽസ്","img":"../../../public/images/tile.png" },
      { "id": 13, "name": "അലൂമിനിയം ഫാബ്രിക്കേഷൻ","img":"../../../public/images/alumnium.png" },
      { "id": 14, "name": "ഗുഡ്സ് ഓട്ടോ" ,"img":"../../../public/images/Ghudsauto.webp"},
      { "id": 15, "name": "തെങ്ങ് കയറ്റം","img":"../../../public/images/coconut.webp" },
      { "id": 17, "name": "ഖിദ്മ സെന്റർ" },
      { "id": 18, "name": "കർഷകർ" ,"img":"../../../public/images/Farmers.jpg" },
      { "id": 19, "name": "ഡോക്ടർസ്","img":"../../../public/images/Docters.png"  },
      { "id": 20, "name": "അധ്യാപകർ" ,"img":"../../../public/images/teachers.jpg"  },
      { "id": 21, "name": "ഉദ്യോഗസ്ഥൻമാർ" ,"img":"../../../public/images/officals.png"},
      { "id": 22, "name": "പൊതു നമ്പറുകൾ" ,"img":"../../../public/images/publicNumbers.png"}
    ],
    "users": [
      { "id": 1, "name": "ശാക്കിർ ഹുസൈൻ", "phone": "8907165792", "category_id": 1 },
      { "id": 2, "name": "ജാഫർ KT", "phone": "9847766840", "category_id": 1 },
      { "id": 3, "name": "നൗഫൽ P", "phone": "9947556642", "category_id": 1 },
      { "id": 4, "name": "ജലീൽ KT", "phone": "9946591138", "category_id": 1 },
      { "id": 5, "name": "മുഹ്സിൻ A", "phone": "9400178002", "category_id": 1 },
      { "id": 6, "name": "ജാഫർ P", "phone": "9744402604", "category_id": 2 },
      { "id": 7, "name": "നവാസ് KT", "phone": "9895232708", "category_id": 2 },
      { "id": 8, "name": "റിൻഷാദ് A", "phone": "9072335105", "category_id": 2 },
      { "id": 9, "name": "ജുനൈദ് KT", "phone": "8943392146", "category_id": 2 },
      { "id": 10, "name": "അഫീൽ PT", "phone": "9744027371", "category_id": 2 },
      { "id": 11, "name": "ശംസുദ്ധീൻ", "phone": "9526112237", "category_id": 2 },
      { "id": 12, "name": "നൗഫൽ PK", "phone": "8943717469", "category_id": 2 },
      { "id": 13, "name": "റിയാസ് K", "phone": "8547293525", "category_id": 2 },
      { "id": 14, "name": "റാഷിദ്‌ MV", "phone": "7034639133", "category_id": 2 },
      { "id": 15, "name": "ആഷിഖ് (നസീഖ്)", "phone": "9037041804", "category_id": 2 },
      { "id": 16, "name": "മുഹമ്മദ്‌ കുട്ടി KT", "phone": "9526137176", "category_id": 3 },
      { "id": 17, "name": "MB ടൂൾസ്", "phone": "", "category_id": 4 },
      { "id": 18, "name": "KTM ബേക്കറി&കൂൾബർ", "phone": "", "category_id": 4 },
      { "id": 19, "name": "i വ ബിരിയാണി സ്റ്റോർ", "phone": "", "category_id": 4 },
      { "id": 20, "name": "i വ ഹോട്ടൽ", "phone": "", "category_id": 4 },
      { "id": 21, "name": "Lovely ഫാഷൻ", "phone": "", "category_id": 4 },
      { "id": 22, "name": "Chai ടീ ഷോപ്പ്", "phone": "", "category_id": 4 },
      { "id": 23, "name": "ബാർബർ ഷോപ്പ്", "phone": "", "category_id": 4 },
      { "id": 24, "name": "ബാർബർ ഷോപ്പ്", "phone": "", "category_id": 4 },
      { "id": 25, "name": "KTM സ്റ്റോർ", "phone": "", "category_id": 4 },
      { "id": 26, "name": "പ്രിയം ടെസ്റ്റയിൽസ്", "phone": "", "category_id": 4 },
      { "id": 27, "name": "Stylo ടൈലറിങ്", "phone": "", "category_id": 4 },
      { "id": 28, "name": "റഹ്മത്ത് സ്റ്റോർ", "phone": "", "category_id": 4 },
      { "id": 30, "name": "ഹോസ്പിറ്റൽ", "phone": "", "category_id": 22 },
      { "id": 31, "name": "മദ്രസ്സ", "phone": "", "category_id": 22 },
      { "id": 32, "name": "പള്ളി", "phone": "", "category_id": 22 },
      { "id": 34, "name": "ട്യൂഷൻ സെന്റർ", "phone": "", "category_id": 22 },
      { "id": 35, "name": "SYS സാന്ത്വനം", "phone": "", "category_id": 22 },
      { "id": 36, "name": "ഖിദ്മ സെന്റർ", "phone": "", "category_id": 22 }
    ]
  }
  